<?xml version="1.0" encoding="UTF-8"?>
<beans xmlns="http://www.springframework.org/schema/beans"
	xmlns:xsi="http://www.w3.org/2001/XMLSchema-instance" xmlns:aop="http://www.springframework.org/schema/aop"
	xsi:schemaLocation="
			http://www.springframework.org/schema/beans http://www.springframework.org/schema/beans/spring-beans.xsd
			http://www.springframework.org/schema/aop http://www.springframework.org/schema/aop/spring-aop.xsd">

	<!-- General validators -->
	<bean id="LightingControlRequestValidator" class="com.sensus.mlc.base.validation.LightingControlRequestValidator" />
	<bean id="lightingControlRequestValidationController" class="com.sensus.common.validation.ValidationController">
		<property name="validators">
			<list>
				<ref bean="LightingControlRequestValidator" />
			</list>
		</property>
	</bean>

	<bean id="LightingControlInquiryRequestValidator" class="com.sensus.mlc.base.validation.LightingControlInquiryRequestValidator">
		<property name="pageSizeList" value= "${system.settings.pageSizeList}" />
	</bean>
	<bean id="lightingControlInquiryRequestValidationController" class="com.sensus.common.validation.ValidationController">
		<property name="validators">
			<list>
				<ref bean="LightingControlInquiryRequestValidator" />
			</list>
		</property>
	</bean>

	<bean id="LightSelectionRequestValidator" class="com.sensus.mlc.base.validation.LightSelectionRequestValidator" />
	<bean id="lightSelectionRequestValidationController" class="com.sensus.common.validation.ValidationController">
		<property name="validators">
			<list>
				<ref bean="LightSelectionRequestValidator" />
			</list>
		</property>
	</bean>

	<bean id="RangeDateValidator" class="com.sensus.mlc.base.validation.RangeDateValidator" />
	<bean id="rangeDateValidationController" class="com.sensus.common.validation.ValidationController">
		<property name="validators">
			<list>
				<ref bean="RangeDateValidator" />
			</list>
		</property>
	</bean>

	<bean id="PropertiesValidator" class="com.sensus.mlc.smartpoint.validation.PropertiesValidator" />
	<bean id="propertiesValidationController" class="com.sensus.common.validation.ValidationController">
		<property name="validators">
			<list>
				<ref bean="PropertiesValidator" />
			</list>
		</property>
	</bean>

	<bean id="CustomSearchValidator" class="com.sensus.mlc.smartpoint.validation.CustomSearchValidator" />
	<bean id="customSearchValidationController" class="com.sensus.common.validation.ValidationController">
		<property name="validators">
			<list>
				<ref bean="CustomSearchValidator" />
			</list>
		</property>
	</bean>

	<bean id="GeoCodeValidator" class="com.sensus.mlc.base.validation.GeoCodeValidator" />
	<bean id="geoCodeValidationController" class="com.sensus.common.validation.ValidationController">
		<property name="validators">
			<list>
				<ref bean="GeoCodeValidator" />
			</list>
		</property>
	</bean>

	<!-- Validators by area -->
	<bean id="LightValidator" class="com.sensus.mlc.smartpoint.validation.LightValidator" />
	<bean id="lightValidationController" class="com.sensus.common.validation.ValidationController">
		<property name="validators">
			<list>
				<ref bean="LightValidator" />
			</list>
		</property>
	</bean>

	<bean id="AnalyticsTypeValidator" class="com.sensus.mlc.analytics.validation.AnalyticsTypeValidator" />
	<bean id="analyticsTypeValidationController" class="com.sensus.common.validation.ValidationController">
		<property name="validators">
			<list>
				<ref bean="AnalyticsTypeValidator" />
			</list>
		</property>
	</bean>

	<!-- Group Validators -->
	<bean id="GroupValidator" class="com.sensus.mlc.group.validation.GroupValidator" />
	<bean id="groupValidationController" class="com.sensus.common.validation.ValidationController">
		<property name="validators">
			<list>
				<ref bean="GroupValidator" />
			</list>
		</property>
	</bean>



<!-- ==================Criado via Sistema Chaveestrangeira================================================================================================- -->
<!-- Chaveestrangeira Validators -->
<bean id="ChaveestrangeiraValidator" class="com.sensus.mlc.chaveestrangeira.validation.ChaveestrangeiraValidator" />
<bean id="chaveestrangeiraValidationController" class="com.sensus.common.validation.ValidationController">
	<property name="validators">
		<list>
			<ref bean="ChaveestrangeiraValidator" />
		</list>
	</property>
</bean>
<bean id="ChaveestrangeiraListValidator" class="com.sensus.mlc.chaveestrangeira.validation.ChaveestrangeiraListValidator" />
<bean id="chaveestrangeiraListValidationController" class="com.sensus.common.validation.ValidationController">
   <property name="validators">
       <list>
	            <ref bean="ChaveestrangeiraListValidator" />
       </list>
   </property>
</bean>
<!-- ===================================================================================================================== -->

<!-- ==================Criado via Sistema Chaveprimaria================================================================================================- -->
<!-- Chaveprimaria Validators -->
<bean id="ChaveprimariaValidator" class="com.sensus.mlc.chaveprimaria.validation.ChaveprimariaValidator" />
<bean id="chaveprimariaValidationController" class="com.sensus.common.validation.ValidationController">
	<property name="validators">
		<list>
			<ref bean="ChaveprimariaValidator" />
		</list>
	</property>
</bean>
<bean id="ChaveprimariaListValidator" class="com.sensus.mlc.chaveprimaria.validation.ChaveprimariaListValidator" />
<bean id="chaveprimariaListValidationController" class="com.sensus.common.validation.ValidationController">
   <property name="validators">
       <list>
	            <ref bean="ChaveprimariaListValidator" />
       </list>
   </property>
</bean>
<!-- ===================================================================================================================== -->

<!-- ==================Criado via Sistema Dominios================================================================================================- -->
<!-- Dominios Validators -->
<bean id="DominiosValidator" class="com.sensus.mlc.dominios.validation.DominiosValidator" />
<bean id="dominiosValidationController" class="com.sensus.common.validation.ValidationController">
	<property name="validators">
		<list>
			<ref bean="DominiosValidator" />
		</list>
	</property>
</bean>
<bean id="DominiosListValidator" class="com.sensus.mlc.dominios.validation.DominiosListValidator" />
<bean id="dominiosListValidationController" class="com.sensus.common.validation.ValidationController">
   <property name="validators">
       <list>
	            <ref bean="DominiosListValidator" />
       </list>
   </property>
</bean>
<!-- ===================================================================================================================== -->

<!-- ==================Criado via Sistema Tabela================================================================================================- -->
<!-- Tabela Validators -->
<bean id="TabelaValidator" class="com.sensus.mlc.tabela.validation.TabelaValidator" />
<bean id="tabelaValidationController" class="com.sensus.common.validation.ValidationController">
	<property name="validators">
		<list>
			<ref bean="TabelaValidator" />
		</list>
	</property>
</bean>
<bean id="TabelaListValidator" class="com.sensus.mlc.tabela.validation.TabelaListValidator" />
<bean id="tabelaListValidationController" class="com.sensus.common.validation.ValidationController">
   <property name="validators">
       <list>
	            <ref bean="TabelaListValidator" />
       </list>
   </property>
</bean>
<!-- ===================================================================================================================== -->

<!-- ==================Criado via Sistema Atributos================================================================================================- -->
<!-- Atributos Validators -->
<bean id="AtributosValidator" class="com.sensus.mlc.atributos.validation.AtributosValidator" />
<bean id="atributosValidationController" class="com.sensus.common.validation.ValidationController">
	<property name="validators">
		<list>
			<ref bean="AtributosValidator" />
		</list>
	</property>
</bean>
<bean id="AtributosListValidator" class="com.sensus.mlc.atributos.validation.AtributosListValidator" />
<bean id="atributosListValidationController" class="com.sensus.common.validation.ValidationController">
   <property name="validators">
       <list>
	            <ref bean="AtributosListValidator" />
       </list>
   </property>
</bean>
<!-- ===================================================================================================================== -->

<!-- ==================Criado via Sistema Tabela================================================================================================- -->
<!-- Tabela Validators -->
<bean id="TabelaValidator" class="com.sensus.mlc.tabela.validation.TabelaValidator" />
<bean id="tabelaValidationController" class="com.sensus.common.validation.ValidationController">
	<property name="validators">
		<list>
			<ref bean="TabelaValidator" />
		</list>
	</property>
</bean>
<bean id="TabelaListValidator" class="com.sensus.mlc.tabela.validation.TabelaListValidator" />
<bean id="tabelaListValidationController" class="com.sensus.common.validation.ValidationController">
   <property name="validators">
       <list>
	            <ref bean="TabelaListValidator" />
       </list>
   </property>
</bean>
<!-- ===================================================================================================================== -->

<!-- ==================Criado via Sistema Tipcliente================================================================================================- -->
<!-- Tipcliente Validators -->
<bean id="TipclienteValidator" class="com.sensus.mlc.tipcliente.validation.TipclienteValidator" />
<bean id="tipclienteValidationController" class="com.sensus.common.validation.ValidationController">
	<property name="validators">
		<list>
			<ref bean="TipclienteValidator" />
		</list>
	</property>
</bean>
<bean id="TipclienteListValidator" class="com.sensus.mlc.tipcliente.validation.TipclienteListValidator" />
<bean id="tipclienteListValidationController" class="com.sensus.common.validation.ValidationController">
   <property name="validators">
       <list>
	            <ref bean="TipclienteListValidator" />
       </list>
   </property>
</bean>
<!-- ===================================================================================================================== -->

<!-- ==================Criado via Sistema Classcliente================================================================================================- -->
<!-- Classcliente Validators -->
<bean id="ClassclienteValidator" class="com.sensus.mlc.classcliente.validation.ClassclienteValidator" />
<bean id="classclienteValidationController" class="com.sensus.common.validation.ValidationController">
	<property name="validators">
		<list>
			<ref bean="ClassclienteValidator" />
		</list>
	</property>
</bean>
<bean id="ClassclienteListValidator" class="com.sensus.mlc.classcliente.validation.ClassclienteListValidator" />
<bean id="classclienteListValidationController" class="com.sensus.common.validation.ValidationController">
   <property name="validators">
       <list>
	            <ref bean="ClassclienteListValidator" />
       </list>
   </property>
</bean>
<!-- ===================================================================================================================== -->

<!-- ==================Criado via Sistema Unimed================================================================================================- -->
<!-- Unimed Validators -->
<bean id="UnimedValidator" class="com.sensus.mlc.unimed.validation.UnimedValidator" />
<bean id="unimedValidationController" class="com.sensus.common.validation.ValidationController">
	<property name="validators">
		<list>
			<ref bean="UnimedValidator" />
		</list>
	</property>
</bean>
<bean id="UnimedListValidator" class="com.sensus.mlc.unimed.validation.UnimedListValidator" />
<bean id="unimedListValidationController" class="com.sensus.common.validation.ValidationController">
   <property name="validators">
       <list>
	            <ref bean="UnimedListValidator" />
       </list>
   </property>
</bean>
<!-- ===================================================================================================================== -->

<!-- ==================Criado via Sistema Embalagens================================================================================================- -->
<!-- Embalagens Validators -->
<bean id="EmbalagensValidator" class="com.sensus.mlc.embalagens.validation.EmbalagensValidator" />
<bean id="embalagensValidationController" class="com.sensus.common.validation.ValidationController">
	<property name="validators">
		<list>
			<ref bean="EmbalagensValidator" />
		</list>
	</property>
</bean>
<bean id="EmbalagensListValidator" class="com.sensus.mlc.embalagens.validation.EmbalagensListValidator" />
<bean id="embalagensListValidationController" class="com.sensus.common.validation.ValidationController">
   <property name="validators">
       <list>
	            <ref bean="EmbalagensListValidator" />
       </list>
   </property>
</bean>
<!-- ===================================================================================================================== -->

<!-- ==================Criado via Sistema Embalagens================================================================================================- -->
<!-- Embalagens Validators -->
<bean id="EmbalagensValidator" class="com.sensus.mlc.embalagens.validation.EmbalagensValidator" />
<bean id="embalagensValidationController" class="com.sensus.common.validation.ValidationController">
	<property name="validators">
		<list>
			<ref bean="EmbalagensValidator" />
		</list>
	</property>
</bean>
<bean id="EmbalagensListValidator" class="com.sensus.mlc.embalagens.validation.EmbalagensListValidator" />
<bean id="embalagensListValidationController" class="com.sensus.common.validation.ValidationController">
   <property name="validators">
       <list>
	            <ref bean="EmbalagensListValidator" />
       </list>
   </property>
</bean>
<!-- ===================================================================================================================== -->

<!-- ==================Criado via Sistema Titulares================================================================================================- -->
<!-- Titulares Validators -->
<bean id="TitularesValidator" class="com.sensus.mlc.titulares.validation.TitularesValidator" />
<bean id="titularesValidationController" class="com.sensus.common.validation.ValidationController">
	<property name="validators">
		<list>
			<ref bean="TitularesValidator" />
		</list>
	</property>
</bean>
<bean id="TitularesListValidator" class="com.sensus.mlc.titulares.validation.TitularesListValidator" />
<bean id="titularesListValidationController" class="com.sensus.common.validation.ValidationController">
   <property name="validators">
       <list>
	            <ref bean="TitularesListValidator" />
       </list>
   </property>
</bean>
<!-- ===================================================================================================================== -->

<!-- ==================Criado via Sistema Eventos================================================================================================- -->
<!-- Eventos Validators -->
<bean id="EventosValidator" class="com.sensus.mlc.eventos.validation.EventosValidator" />
<bean id="eventosValidationController" class="com.sensus.common.validation.ValidationController">
	<property name="validators">
		<list>
			<ref bean="EventosValidator" />
		</list>
	</property>
</bean>
<bean id="EventosListValidator" class="com.sensus.mlc.eventos.validation.EventosListValidator" />
<bean id="eventosListValidationController" class="com.sensus.common.validation.ValidationController">
   <property name="validators">
       <list>
	            <ref bean="EventosListValidator" />
       </list>
   </property>
</bean>
<!-- ===================================================================================================================== -->

<!-- ==================Criado via Sistema Pais================================================================================================- -->
<!-- Pais Validators -->
<bean id="PaisValidator" class="com.sensus.mlc.pais.validation.PaisValidator" />
<bean id="paisValidationController" class="com.sensus.common.validation.ValidationController">
	<property name="validators">
		<list>
			<ref bean="PaisValidator" />
		</list>
	</property>
</bean>
<bean id="PaisListValidator" class="com.sensus.mlc.pais.validation.PaisListValidator" />
<bean id="paisListValidationController" class="com.sensus.common.validation.ValidationController">
   <property name="validators">
       <list>
	            <ref bean="PaisListValidator" />
       </list>
   </property>
</bean>
<!-- ===================================================================================================================== -->

<!-- ==================Criado via Sistema Uf================================================================================================- -->
<!-- Uf Validators -->
<bean id="UfValidator" class="com.sensus.mlc.uf.validation.UfValidator" />
<bean id="ufValidationController" class="com.sensus.common.validation.ValidationController">
	<property name="validators">
		<list>
			<ref bean="UfValidator" />
		</list>
	</property>
</bean>
<bean id="UfListValidator" class="com.sensus.mlc.uf.validation.UfListValidator" />
<bean id="ufListValidationController" class="com.sensus.common.validation.ValidationController">
   <property name="validators">
       <list>
	            <ref bean="UfListValidator" />
       </list>
   </property>
</bean>
<!-- ===================================================================================================================== -->

<!-- ==================Criado via Sistema Municipio================================================================================================- -->
<!-- Municipio Validators -->
<bean id="MunicipioValidator" class="com.sensus.mlc.municipio.validation.MunicipioValidator" />
<bean id="municipioValidationController" class="com.sensus.common.validation.ValidationController">
	<property name="validators">
		<list>
			<ref bean="MunicipioValidator" />
		</list>
	</property>
</bean>
<bean id="MunicipioListValidator" class="com.sensus.mlc.municipio.validation.MunicipioListValidator" />
<bean id="municipioListValidationController" class="com.sensus.common.validation.ValidationController">
   <property name="validators">
       <list>
	            <ref bean="MunicipioListValidator" />
       </list>
   </property>
</bean>
<!-- ===================================================================================================================== -->

<!-- ==================Criado via Sistema Municipio================================================================================================- -->
<!-- Municipio Validators -->
<bean id="MunicipioValidator" class="com.sensus.mlc.municipio.validation.MunicipioValidator" />
<bean id="municipioValidationController" class="com.sensus.common.validation.ValidationController">
	<property name="validators">
		<list>
			<ref bean="MunicipioValidator" />
		</list>
	</property>
</bean>
<bean id="MunicipioListValidator" class="com.sensus.mlc.municipio.validation.MunicipioListValidator" />
<bean id="municipioListValidationController" class="com.sensus.common.validation.ValidationController">
   <property name="validators">
       <list>
	            <ref bean="MunicipioListValidator" />
       </list>
   </property>
</bean>
<!-- ===================================================================================================================== -->

<!-- ==================Criado via Sistema Bairro================================================================================================- -->
<!-- Bairro Validators -->
<bean id="BairroValidator" class="com.sensus.mlc.bairro.validation.BairroValidator" />
<bean id="bairroValidationController" class="com.sensus.common.validation.ValidationController">
	<property name="validators">
		<list>
			<ref bean="BairroValidator" />
		</list>
	</property>
</bean>
<bean id="BairroListValidator" class="com.sensus.mlc.bairro.validation.BairroListValidator" />
<bean id="bairroListValidationController" class="com.sensus.common.validation.ValidationController">
   <property name="validators">
       <list>
	            <ref bean="BairroListValidator" />
       </list>
   </property>
</bean>
<!-- ===================================================================================================================== -->

<!-- ==================Criado via Sistema Cnae================================================================================================- -->
<!-- Cnae Validators -->
<bean id="CnaeValidator" class="com.sensus.mlc.cnae.validation.CnaeValidator" />
<bean id="cnaeValidationController" class="com.sensus.common.validation.ValidationController">
	<property name="validators">
		<list>
			<ref bean="CnaeValidator" />
		</list>
	</property>
</bean>
<bean id="CnaeListValidator" class="com.sensus.mlc.cnae.validation.CnaeListValidator" />
<bean id="cnaeListValidationController" class="com.sensus.common.validation.ValidationController">
   <property name="validators">
       <list>
	            <ref bean="CnaeListValidator" />
       </list>
   </property>
</bean>
<!-- ===================================================================================================================== -->

<!-- ==================Criado via Sistema Endereco================================================================================================- -->
<!-- Endereco Validators -->
<bean id="EnderecoValidator" class="com.sensus.mlc.endereco.validation.EnderecoValidator" />
<bean id="enderecoValidationController" class="com.sensus.common.validation.ValidationController">
	<property name="validators">
		<list>
			<ref bean="EnderecoValidator" />
		</list>
	</property>
</bean>
<bean id="EnderecoListValidator" class="com.sensus.mlc.endereco.validation.EnderecoListValidator" />
<bean id="enderecoListValidationController" class="com.sensus.common.validation.ValidationController">
   <property name="validators">
       <list>
	            <ref bean="EnderecoListValidator" />
       </list>
   </property>
</bean>
<!-- ===================================================================================================================== -->

<!-- ==================Criado via Sistema Filial================================================================================================- -->
<!-- Filial Validators -->
<bean id="FilialValidator" class="com.sensus.mlc.filial.validation.FilialValidator" />
<bean id="filialValidationController" class="com.sensus.common.validation.ValidationController">
	<property name="validators">
		<list>
			<ref bean="FilialValidator" />
		</list>
	</property>
</bean>
<bean id="FilialListValidator" class="com.sensus.mlc.filial.validation.FilialListValidator" />
<bean id="filialListValidationController" class="com.sensus.common.validation.ValidationController">
   <property name="validators">
       <list>
	            <ref bean="FilialListValidator" />
       </list>
   </property>
</bean>
<!-- ===================================================================================================================== -->

<!-- ==================Criado via Sistema Empresa================================================================================================- -->
<!-- Empresa Validators -->
<bean id="EmpresaValidator" class="com.sensus.mlc.empresa.validation.EmpresaValidator" />
<bean id="empresaValidationController" class="com.sensus.common.validation.ValidationController">
	<property name="validators">
		<list>
			<ref bean="EmpresaValidator" />
		</list>
	</property>
</bean>
<bean id="EmpresaListValidator" class="com.sensus.mlc.empresa.validation.EmpresaListValidator" />
<bean id="empresaListValidationController" class="com.sensus.common.validation.ValidationController">
   <property name="validators">
       <list>
	            <ref bean="EmpresaListValidator" />
       </list>
   </property>
</bean>
<!-- ===================================================================================================================== -->

<!-- ==================Criado via Sistema Chaveestrangeira================================================================================================- -->
<!-- Chaveestrangeira Validators -->
<bean id="ChaveestrangeiraValidator" class="com.sensus.mlc.chaveestrangeira.validation.ChaveestrangeiraValidator" />
<bean id="chaveestrangeiraValidationController" class="com.sensus.common.validation.ValidationController">
	<property name="validators">
		<list>
			<ref bean="ChaveestrangeiraValidator" />
		</list>
	</property>
</bean>
<bean id="ChaveestrangeiraListValidator" class="com.sensus.mlc.chaveestrangeira.validation.ChaveestrangeiraListValidator" />
<bean id="chaveestrangeiraListValidationController" class="com.sensus.common.validation.ValidationController">
   <property name="validators">
       <list>
	            <ref bean="ChaveestrangeiraListValidator" />
       </list>
   </property>
</bean>
<!-- ===================================================================================================================== -->

<!-- ==================Criado via Sistema Dominios================================================================================================- -->
<!-- Dominios Validators -->
<bean id="DominiosValidator" class="com.sensus.mlc.dominios.validation.DominiosValidator" />
<bean id="dominiosValidationController" class="com.sensus.common.validation.ValidationController">
	<property name="validators">
		<list>
			<ref bean="DominiosValidator" />
		</list>
	</property>
</bean>
<bean id="DominiosListValidator" class="com.sensus.mlc.dominios.validation.DominiosListValidator" />
<bean id="dominiosListValidationController" class="com.sensus.common.validation.ValidationController">
   <property name="validators">
       <list>
	            <ref bean="DominiosListValidator" />
       </list>
   </property>
</bean>
<!-- ===================================================================================================================== -->

<!-- ==================Criado via Sistema Dominios================================================================================================- -->
<!-- Dominios Validators -->
<bean id="DominiosValidator" class="com.sensus.mlc.dominios.validation.DominiosValidator" />
<bean id="dominiosValidationController" class="com.sensus.common.validation.ValidationController">
	<property name="validators">
		<list>
			<ref bean="DominiosValidator" />
		</list>
	</property>
</bean>
<bean id="DominiosListValidator" class="com.sensus.mlc.dominios.validation.DominiosListValidator" />
<bean id="dominiosListValidationController" class="com.sensus.common.validation.ValidationController">
   <property name="validators">
       <list>
	            <ref bean="DominiosListValidator" />
       </list>
   </property>
</bean>
<!-- ===================================================================================================================== -->

<!-- ==================Criado via Sistema Atributos================================================================================================- -->
<!-- Atributos Validators -->
<bean id="AtributosValidator" class="com.sensus.mlc.atributos.validation.AtributosValidator" />
<bean id="atributosValidationController" class="com.sensus.common.validation.ValidationController">
	<property name="validators">
		<list>
			<ref bean="AtributosValidator" />
		</list>
	</property>
</bean>
<bean id="AtributosListValidator" class="com.sensus.mlc.atributos.validation.AtributosListValidator" />
<bean id="atributosListValidationController" class="com.sensus.common.validation.ValidationController">
   <property name="validators">
       <list>
	            <ref bean="AtributosListValidator" />
       </list>
   </property>
</bean>
<!-- ===================================================================================================================== -->

<!-- ==================Criado via Sistema Tabela================================================================================================- -->
<!-- Tabela Validators -->
<bean id="TabelaValidator" class="com.sensus.mlc.Tabela.validation.TabelaValidator" />
<bean id="TabelaValidationController" class="com.sensus.common.validation.ValidationController">
	<property name="validators">
		<list>
			<ref bean="TabelaValidator" />
		</list>
	</property>
</bean>
<bean id="TabelaListValidator" class="com.sensus.mlc.Tabela.validation.TabelaListValidator" />
<bean id="TabelaListValidationController" class="com.sensus.common.validation.ValidationController">
   <property name="validators">
       <list>
	            <ref bean="TabelaListValidator" />
       </list>
   </property>
</bean>
<!-- ===================================================================================================================== -->



	<bean id="GroupRequestValidator" class="com.sensus.mlc.group.validation.GroupRequestValidator" />
	<bean id="groupRequestValidationController" class="com.sensus.common.validation.ValidationController">
		<property name="validators">
			<list>
				<ref bean="GroupRequestValidator" />
			</list>
		</property>
	</bean>

	<bean id="GroupListValidator" class="com.sensus.mlc.group.validation.GroupListValidator" />
	<bean id="groupListValidationController" class="com.sensus.common.validation.ValidationController">
		<property name="validators">
			<list>
				<ref bean="GroupListValidator" />
			</list>
		</property>
	</bean>

	<bean id="ScheduleValidator" class="com.sensus.mlc.schedule.validation.ScheduleValidator" >
		<property name="scheduleBCL" ref="scheduleBCLTarget" />
	</bean>

	<bean id="scheduleValidationController" class="com.sensus.common.validation.ValidationController">
		<property name="validators">
			<list>
				<ref bean="ScheduleValidator" />
			</list>
		</property>
	</bean>

	<bean id="MapDataValidator" class="com.sensus.mlc.base.validation.MapDataValidator" />
	<bean id="mapDataValidationController" class="com.sensus.common.validation.ValidationController">
		<property name="validators">
			<list>
				<ref bean="MapDataValidator" />
			</list>
		</property>
	</bean>

	<bean id="LightListValidator" class="com.sensus.mlc.smartpoint.validation.LightListValidator" />
	<bean id="lightListValidationController" class="com.sensus.common.validation.ValidationController">
		<property name="validators">
			<list>
				<ref bean="LightListValidator" />
			</list>
		</property>
	</bean>

	<bean id="ProcessValidator" class="com.sensus.mlc.process.validation.ProcessValidator" />
	<bean id="processValidationController" class="com.sensus.common.validation.ValidationController">
		<property name="validators">
			<list>
				<ref bean="ProcessValidator" />
			</list>
		</property>
	</bean>

	<bean id="ColumnFilterValidator" class="com.sensus.mlc.base.validation.ColumnFilterValidator" />
		<bean id="columnFilterValidationController" class="com.sensus.common.validation.ValidationController">
		<property name="validators">
			<list>
				<ref bean="ColumnFilterValidator" />
			</list>
		</property>
	</bean>

	<bean id="LightStatusNotificationRequestValidator" class="com.sensus.mlc.smartpoint.validation.LightStatusNotificationRequestValidator" />
	<bean id="lightStatusNotificationRequestValidationController" class="com.sensus.common.validation.ValidationController">
		<property name="validators">
			<list>
				<ref bean="LightStatusNotificationRequestValidator" />
			</list>
		</property>
	</bean>

	<bean id="ChannelSetupAuditRequestValidator" class="com.sensus.mlc.smartpoint.validation.ChannelSetupAuditRequestValidator" />
	<bean id="channelSetupAuditRequestValidationController" class="com.sensus.common.validation.ValidationController">
		<property name="validators">
			<list>
				<ref bean="ChannelSetupAuditRequestValidator" />
			</list>
		</property>
	</bean>

	<bean id="AlarmNotificationRequestValidator" class="com.sensus.mlc.smartpoint.validation.AlarmNotificationRequestValidator" />
	<bean id="alarmNotificationRequestValidationController" class="com.sensus.common.validation.ValidationController">
		<property name="validators">
			<list>
				<ref bean="AlarmNotificationRequestValidator" />
			</list>
		</property>
	</bean>

	<bean id="ForcedLightStatusNotificationRequestValidator" class="com.sensus.mlc.smartpoint.validation.ForcedLightStatusNotificationRequestValidator" />
	<bean id="forcedLightStatusNotificationRequestValidationController" class="com.sensus.common.validation.ValidationController">
		<property name="validators">
			<list>
				<ref bean="ForcedLightStatusNotificationRequestValidator" />
			</list>
		</property>
	</bean>

	<bean id="LightIntensityValidator" class="com.sensus.mlc.smartpoint.validation.LightIntensityValidator" />
	<bean id="lightIntensityValidationController" class="com.sensus.common.validation.ValidationController">
		<property name="validators">
			<list>
				<ref bean="LightIntensityValidator" />
			</list>
		</property>
	</bean>


	<bean id="MlcGatewaySupervisoryNotificationValidator" class="com.sensus.mlc.mlcserver.validation.MlcGatewaySupervisoryNotificationValidator" />
	<bean id="mlcGatewaySupervisoryNotificationValidationController" class="com.sensus.common.validation.ValidationController">
		<property name="validators">
			<list>
				<ref bean="MlcGatewaySupervisoryNotificationValidator" />
			</list>
		</property>
	</bean>

	<bean id="MlcServerValidator" class="com.sensus.mlc.mlcserver.validation.MlcServerValidator" />
	<bean id="mlcServerValidationController" class="com.sensus.common.validation.ValidationController">
		<property name="validators">
			<list>
				<ref bean="MlcServerValidator" />
			</list>
		</property>
	</bean>

	<bean id="TenantLightAssociationValidator" class="com.sensus.mlc.base.validation.TenantLightAssociationValidator">

	</bean>
	<bean id="tenantLightAssociationValidationController" class="com.sensus.common.validation.ValidationController">
		<property name="validators">
			<list>
				<ref bean="TenantLightAssociationValidator" />
			</list>
		</property>
	</bean>

	<bean id="SettingListValidator" class="com.sensus.mlc.settings.validation.SettingListValidator" />
	<bean id="settingListValidationController" class="com.sensus.common.validation.ValidationController">
		<property name="validators">
			<list>
				<ref bean="SettingListValidator" />
			</list>
		</property>
	</bean>

	<bean id="UserValidator" class="com.sensus.mlc.user.validation.UserValidator" />
	<bean id="userValidationController" class="com.sensus.common.validation.ValidationController">
		<property name="validators">
			<list>
				<ref bean="UserValidator" />
			</list>
		</property>
	</bean>

	<bean id="UserRequestValidator" class="com.sensus.mlc.user.validation.UserRequestValidator" />
	<bean id="userRequestValidationController" class="com.sensus.common.validation.ValidationController">
		<property name="validators">
			<list>
				<ref bean="UserRequestValidator" />
			</list>
		</property>
	</bean>

	<bean id="TagRequestValidator" class="com.sensus.mlc.tag.validation.TagRequestValidator" />
	<bean id="tagRequestValidationController" class="com.sensus.common.validation.ValidationController">
		<property name="validators">
			<list>
				<ref bean="TagRequestValidator" />
			</list>
		</property>
	</bean>

	<bean id="TagValidator" class="com.sensus.mlc.tag.validation.TagValidator" />
	<bean id="tagValidationController" class="com.sensus.common.validation.ValidationController">
		<property name="validators">
			<list>
				<ref bean="TagValidator" />
			</list>
		</property>
	</bean>

	<bean id="TagListValidator" class="com.sensus.mlc.tag.validation.TagListValidator" />
	<bean id="tagListValidationController" class="com.sensus.common.validation.ValidationController">
		<property name="validators">
			<list>
				<ref bean="TagListValidator" />
			</list>
		</property>
	</bean>

	<bean id="TenantRequestValidator" class="com.sensus.mlc.tenant.validation.TenantRequestValidator" />
	<bean id="tenantRequestValidationController" class="com.sensus.common.validation.ValidationController">
		<property name="validators">
			<list>
				<ref bean="TenantRequestValidator" />
			</list>
		</property>
	</bean>

	<bean id="ecomodeValidationController" class="com.sensus.common.validation.ValidationController">
		<property name="validators">
			<list>
				<ref bean="LightingControlRequestValidator" />
				<ref bean="LightingControlInquiryRequestValidator" />
			</list>
		</property>
	</bean>

	<bean id="EcoModeBaselineValidator" class="com.sensus.mlc.ecomode.validation.EcoModeBaselineValidator" />
	<bean id="ecoModeBaselineValidationController" class="com.sensus.common.validation.ValidationController">
		<property name="validators">
			<list>
				<ref bean="EcoModeBaselineValidator" />
			</list>
		</property>
	</bean>

	<bean id="CsvFileValidator" class="com.sensus.mlc.base.validation.CsvFileValidator" />
	<bean id="csvFileValidationController" class="com.sensus.common.validation.ValidationController">
		<property name="validators">
			<list>
				<ref bean="CsvFileValidator" />
			</list>
		</property>
	</bean>
</beans>



























