<?xml version="1.0" encoding="UTF-8" ?>

<!DOCTYPE mapper
    PUBLIC "-//mybatis.org//DTD Mapper 3.0//EN"
    "http://mybatis.org/dtd/mybatis-3-mapper.dtd">

<mapper namespace="TelefoneMap">

	<!-- <cache type="org.mybatis.caches.ehcache.LoggingEhcache"/>
	<cache type="org.mybatis.caches.ehcache.EhcacheCache"/>  -->

  	<!-- Result maps describe the mapping between the columns returned
       from a query, and the class properties.  A result map isn't
       necessary if the columns (or aliases) match to the properties
       exactly. -->

  <resultMap id="telefoneResult" type="Telefone">
    <result property="id" column="id" />
    <result property="typeValue" column="type" />
    <result property="parentId" column="parentId" />
   	<result property="tabelaEnumValue" column="tabela"/>
	<result property="ddd" column="ddd"/>
	<result property="telefone" column="telefone" />
    <result property="create_date" column="create_date" />
   	<result property="create_user" column="create_user"/>
	<result property="modify_date" column="modify_date"/>
	<result property="modify_user" column="modify_user"/>

  </resultMap>

  <!--
		SQL fragments allow "parts" of SQL to be re-used in other SQL statements.
	-->
  <sql id="allTelefoneColumns">
		 b.id
		,b.type
		,b.parentId
		,b.tabela
		,b.ddd
		,b.telefone
      	,b.create_date
      	,b.create_user
      	,b.modify_date
      	,b.modify_user
  </sql>

  <sql id="allTelefoneValues">
  		#{id},
    	#{typeValue},
    	#{parentId},
    	#{tabelaEnumValue},
    	#{ddd},
    	#{telefone},
    	<include refid="CBOFMap.changeControlFields"/>
  </sql>


  <!--
		SQL Insert Statements.
 	-->
  <insert id="insertTelefone" parameterType="Telefone" useGeneratedKeys="true" keyProperty="id">
  	INSERT INTO telefone (
		<include refid="allTelefoneColumns" />
      )
    VALUES (<include refid="allTelefoneValues" /> )
  </insert>


	<!--
		SQL Update Statements.
 	-->

  <update id="updateTelefone" parameterType="Telefone">
    UPDATE telefone
    	<set>
    		<if test="ddd!= null">ddd = #{ddd},</if>
	    	<if test="typeValue!= null"> type=#{typeValue},</if>
	    	<if test="telefone!= null"> telefone=#{telefone},</if>
			<if test="modifyDateUTC!= null"> modify_date=#{modifyDateUTC},</if>
			<if test="modifyUser!= null"> modify_user=#{modifyUser}</if>
		</set>
    WHERE
     id = #{id}
  </update>

   <!--
		SQL Delete Statements.
   -->
  <delete id="deleteTelefoneById" parameterType="Integer">
    	DELETE FROM telefone WHERE id = #{id}
  </delete>

	<!--
		SQL Fetch Statements.
 	-->
  <select id="fetchTelefoneByEmpresa" parameterType="Integer" resultMap="telefoneResult">
     SELECT * FROM telefone
     WHERE tabela = 1 and parentId = #{id}
  </select>

  <select id="fetchTelefoneByFuncionario" parameterType="Integer" resultMap="telefoneResult">
     SELECT * FROM telefone
     WHERE tabela = 2 and parentId = #{id}
  </select>



</mapper>