<?xml version="1.0" encoding="UTF-8"?>
<!DOCTYPE configuration
    PUBLIC "-//mybatis.org//DTD Config 3.0//EN"
    "http://mybatis.org/dtd/mybatis-3-config.dtd">

<configuration>

  	<settings>
		<setting name="lazyLoadingEnabled" value="false" />
		<setting name="defaultExecutorType" value="REUSE"/>
	</settings>

  	<typeAliases>

		<typeAlias alias="QATModel"  									 type="com.qat.framework.model.QATModel" />
		<typeAlias alias="QATModelOL"							         type="com.qat.framework.model.QATModelOL" />
		<typeAlias alias="AcaoEnum"									 	 type="com.prosperitasglobal.sendsolv.model.AcaoEnum" />
		<typeAlias alias="Alerta"									 	 type="com.prosperitasglobal.sendsolv.model.Alertas" />
		<typeAlias alias="CfopTypeEnum"									 type="com.prosperitasglobal.sendsolv.model.CfopTypeEnum" />
		<typeAlias alias="TabelaEnum"									 type="com.prosperitasglobal.sendsolv.model.TabelaEnum" />
		<typeAlias alias="TypeEnum"									 	 type="com.prosperitasglobal.sendsolv.model.TypeEnum" />
		<typeAlias alias="PessoaTypeEnum"							 	 type="com.prosperitasglobal.sendsolv.model.PessoaTypeEnum" />
	    <typeAlias alias="EntidadeTypeEnum"							 	 type="com.prosperitasglobal.sendsolv.model.EntidadeTypeEnum" />
		<typeAlias alias="PagedInquiryRequest"     						 type="com.prosperitasglobal.sendsolv.model.request.PagedInquiryRequest"/>
		<typeAlias alias="ProdutoInquiryRequest"     					 type="com.prosperitasglobal.sendsolv.model.request.ProdutoInquiryRequest"/>
		<typeAlias alias="ContasInquiryRequest"     					 type="com.prosperitasglobal.sendsolv.model.request.ContasInquiryRequest"/>
		<typeAlias alias="NotaFiscalInquiryRequest"     				 type="com.prosperitasglobal.sendsolv.model.request.NotaFiscalInquiryRequest"/>
		<typeAlias alias="OrcamentoInquiryRequest"     					 type="com.prosperitasglobal.sendsolv.model.request.OrcamentoInquiryRequest"/>
		<typeAlias alias="PedidoComprasInquiryRequest"     				 type="com.prosperitasglobal.sendsolv.model.request.PedidoComprasInquiryRequest"/>
		<typeAlias alias="HistoricoInquiryRequest"     				 	 type="com.prosperitasglobal.sendsolv.model.request.HistoricoInquiryRequest"/>
		<typeAlias alias="OrdemServicoInquiryRequest"     				 type="com.prosperitasglobal.sendsolv.model.request.OrdemServicoInquiryRequest"/>
		<typeAlias alias="TelaInquiryRequest"     				 		 type="com.prosperitasglobal.sendsolv.model.request.TelaInquiryRequest"/>
		<typeAlias alias="DepositoInquiryRequest"     				 	 type="com.prosperitasglobal.sendsolv.model.request.DepositoInquiryRequest"/>
		<typeAlias alias="FilialInquiryRequest"     				 	 type="com.prosperitasglobal.sendsolv.model.request.FilialInquiryRequest"/>
		<typeAlias alias="PlanoInquiryRequest"     				 		 type="com.prosperitasglobal.sendsolv.model.request.PlanoInquiryRequest"/>

		<typeAlias alias="UniMedInquiryRequest"     				 	type="com.prosperitasglobal.sendsolv.model.request.UniMedInquiryRequest"/>
		<typeAlias alias="GrupoInquiryRequest"     				 		type="com.prosperitasglobal.sendsolv.model.request.GrupoInquiryRequest"/>
		<typeAlias alias="SubGrupoInquiryRequest"     				 	type="com.prosperitasglobal.sendsolv.model.request.SubGrupoInquiryRequest"/>
		<typeAlias alias="MarcaInquiryRequest"     				 		type="com.prosperitasglobal.sendsolv.model.request.MarcaInquiryRequest"/>
		<typeAlias alias="CfopInquiryRequest"     				 		type="com.prosperitasglobal.sendsolv.model.request.CfopInquiryRequest"/>
		<typeAlias alias="CidadeInquiryRequest"     				 	type="com.prosperitasglobal.sendsolv.model.request.CidadeInquiryRequest"/>
		<typeAlias alias="EstadoInquiryRequest"     				 	type="com.prosperitasglobal.sendsolv.model.request.EstadoInquiryRequest"/>
		<typeAlias alias="TributacaoInquiryRequest"     				type="com.prosperitasglobal.sendsolv.model.request.TributacaoInquiryRequest"/>
		<typeAlias alias="ClassificacaoInquiryRequest"     				type="com.prosperitasglobal.sendsolv.model.request.ClassificacaoInquiryRequest"/>
		<typeAlias alias="BancoInquiryRequest"     				 		type="com.prosperitasglobal.sendsolv.model.request.BancoInquiryRequest"/>
		<typeAlias alias="AgenciaInquiryRequest"     				 	type="com.prosperitasglobal.sendsolv.model.request.AgenciaInquiryRequest"/>
		<typeAlias alias="ContaInquiryRequest"     				 		type="com.prosperitasglobal.sendsolv.model.request.ContaInquiryRequest"/>
		<typeAlias alias="BeneficiosInquiryRequest"     				type="com.prosperitasglobal.sendsolv.model.request.BeneficiosInquiryRequest"/>
		<typeAlias alias="EventoInquiryRequest"     				 	type="com.prosperitasglobal.sendsolv.model.request.EventoInquiryRequest"/>
		<typeAlias alias="FormaPgInquiryRequest"     				 	type="com.prosperitasglobal.sendsolv.model.request.FormaPgInquiryRequest"/>
		<typeAlias alias="HoraFuncInquiryRequest"     				 	type="com.prosperitasglobal.sendsolv.model.request.HoraFuncInquiryRequest"/>
		<typeAlias alias="CaixaInquiryRequest"     				 		type="com.prosperitasglobal.sendsolv.model.request.CaixaInquiryRequest"/>
		<typeAlias alias="ConvenioInquiryRequest"     				 	type="com.prosperitasglobal.sendsolv.model.request.ConvenioInquiryRequest"/>
		<typeAlias alias="AlertasInquiryRequest"     				 	type="com.prosperitasglobal.sendsolv.model.request.AlertasInquiryRequest"/>



		<typeAlias alias="Arquivo"              					 type="com.prosperitasglobal.sendsolv.model.Arquivo"/>
		<typeAlias alias="Agencia"              					 type="com.prosperitasglobal.sendsolv.model.Agencia"/>
		<typeAlias alias="Banco"              				 		 type="com.prosperitasglobal.sendsolv.model.Banco"/>
		<typeAlias alias="BancoPessoa"              		 		 type="com.prosperitasglobal.sendsolv.model.BancoPessoa"/>
		<typeAlias alias="Beneficios"              				 	 type="com.prosperitasglobal.sendsolv.model.Beneficios"/>
		<typeAlias alias="BeneficioPessoa"              		 	 type="com.prosperitasglobal.sendsolv.model.BeneficioPessoa"/>
		<typeAlias alias="Caixa"              				 		 type="com.prosperitasglobal.sendsolv.model.Caixa"/>
		<typeAlias alias="Cidade"              				 		 type="com.prosperitasglobal.sendsolv.model.Cidade"/>
		<typeAlias alias="Conta"              				 		 type="com.prosperitasglobal.sendsolv.model.Conta"/>
		<typeAlias alias="Cfop"              				 		 type="com.prosperitasglobal.sendsolv.model.Cfop"/>
		<typeAlias alias="CfopPessoa"              			 		 type="com.prosperitasglobal.sendsolv.model.CfopPessoa"/>
		<typeAlias alias="Classificacao"              				 type="com.prosperitasglobal.sendsolv.model.Classificacao"/>
		<typeAlias alias="Cliente"              				 	 type="com.prosperitasglobal.sendsolv.model.Cliente"/>
		<typeAlias alias="Cnae"              				 		 type="com.prosperitasglobal.sendsolv.model.Cnae"/>
		<typeAlias alias="CnaeEmpresa"              				 type="com.prosperitasglobal.sendsolv.model.CnaeEmpresa"/>
		<typeAlias alias="CondPag"              				 	 type="com.prosperitasglobal.sendsolv.model.CondPag"/>
		<typeAlias alias="CondPagPessoa"            			 	 type="com.prosperitasglobal.sendsolv.model.CondPagPessoa"/>
		<typeAlias alias="ConhecimentoTransporte"              		 type="com.prosperitasglobal.sendsolv.model.ConhecimentoTransporte"/>
		<typeAlias alias="Contas"              				         type="com.prosperitasglobal.sendsolv.model.Contas"/>
		<typeAlias alias="Contato"              				 	 type="com.prosperitasglobal.sendsolv.model.Contato"/>
		<typeAlias alias="ContatoItens"              			 	 type="com.prosperitasglobal.sendsolv.model.ContatoItens"/>
		<typeAlias alias="Convenio"              				 	 type="com.prosperitasglobal.sendsolv.model.Convenio"/>
		<typeAlias alias="ConvenioPessoa"              			 	 type="com.prosperitasglobal.sendsolv.model.ConvenioPessoa"/>
		<typeAlias alias="Cst"              				 		 type="com.prosperitasglobal.sendsolv.model.Cst"/>
		<typeAlias alias="Custo"              				 		 type="com.prosperitasglobal.sendsolv.model.Custo"/>
		<typeAlias alias="CustoItem"              				 	 type="com.prosperitasglobal.sendsolv.model.CustoItem"/>
		<typeAlias alias="Deposito"              				 	 type="com.prosperitasglobal.sendsolv.model.Deposito"/>
		<typeAlias alias="Documento"              				 	 type="com.prosperitasglobal.sendsolv.model.Documento"/>
		<typeAlias alias="Email"              				 		 type="com.prosperitasglobal.sendsolv.model.Email"/>
		<typeAlias alias="Entidade"              				 	 type="com.prosperitasglobal.sendsolv.model.Entidade"/>
		<typeAlias alias="Empresa"              				 	 type="com.prosperitasglobal.sendsolv.model.Empresa"/>
		<typeAlias alias="Endereco"              				 	 type="com.prosperitasglobal.sendsolv.model.Endereco"/>
		<typeAlias alias="Estado"              				 	     type="com.prosperitasglobal.sendsolv.model.Estado"/>
		<typeAlias alias="Estoque"              				 	 type="com.prosperitasglobal.sendsolv.model.Estoque"/>
		<typeAlias alias="Eventos"              				 	 type="com.prosperitasglobal.sendsolv.model.Eventos"/>
		<typeAlias alias="EventoPessoa"              			 	 type="com.prosperitasglobal.sendsolv.model.EventoPessoa"/>
		<typeAlias alias="Field"              				 		 type="com.prosperitasglobal.sendsolv.model.Field"/>
		<typeAlias alias="Filial"              				 		 type="com.prosperitasglobal.sendsolv.model.Filial"/>
		<typeAlias alias="FieldBusca"              				 	 type="com.prosperitasglobal.sendsolv.model.FieldBusca"/>
		<typeAlias alias="Financeiro"              				 	 type="com.prosperitasglobal.sendsolv.model.Financeiro"/>
		<typeAlias alias="FormaPg"              				 	 type="com.prosperitasglobal.sendsolv.model.FormaPg"/>
		<typeAlias alias="FormaPgPessoa"              			 	 type="com.prosperitasglobal.sendsolv.model.FormaPgPessoa"/>
		<typeAlias alias="Fornecedor"              				 	 type="com.prosperitasglobal.sendsolv.model.Fornecedor"/>
		<typeAlias alias="Funcionario"              				 type="com.prosperitasglobal.sendsolv.model.Funcionario"/>
		<typeAlias alias="Grupo"              				 		 type="com.prosperitasglobal.sendsolv.model.Grupo"/>
		<typeAlias alias="GrupoProd"            			 		 type="com.prosperitasglobal.sendsolv.model.GrupoProd"/>
		<typeAlias alias="Historico"              				 	 type="com.prosperitasglobal.sendsolv.model.Historico"/>
		<typeAlias alias="HistoricoNF"              			 	 type="com.prosperitasglobal.sendsolv.model.HistoricoNF"/>
		<typeAlias alias="HistoricoItens"              			 	 type="com.prosperitasglobal.sendsolv.model.HistoricoItens"/>
		<typeAlias alias="HorarioFunc"              			 	 type="com.prosperitasglobal.sendsolv.model.HorarioFunc"/>
		<typeAlias alias="Incidencia"              				 	 type="com.prosperitasglobal.sendsolv.model.Incidencia"/>
		<typeAlias alias="ItensEspeciais"              				 type="com.prosperitasglobal.sendsolv.model.ItensEspeciais"/>
		<typeAlias alias="Marca"              				 		 type="com.prosperitasglobal.sendsolv.model.Marca"/>
		<typeAlias alias="MarcaProd"              				 	 type="com.prosperitasglobal.sendsolv.model.MarcaProd"/>
		<typeAlias alias="NFStatus"              					 type="com.prosperitasglobal.sendsolv.model.NFStatus"/>
		<typeAlias alias="NotaFiscal"              					 type="com.prosperitasglobal.sendsolv.model.NotaFiscal"/>
		<typeAlias alias="NotaFiscalEntrada"              			 type="com.prosperitasglobal.sendsolv.model.NotaFiscalEntrada"/>
		<typeAlias alias="NotaFiscalSaida"              			 type="com.prosperitasglobal.sendsolv.model.NotaFiscalSaida"/>
		<typeAlias alias="Note"              					     type="com.prosperitasglobal.cbof.model.Note"/>
		<typeAlias alias="NotaFiscalItens"              	 		 type="com.prosperitasglobal.sendsolv.model.NotaFiscalItens"/>
		<typeAlias alias="Orcamento"              					 type="com.prosperitasglobal.sendsolv.model.Orcamento"/>
		<typeAlias alias="OrdemServicoTypes"              		 	 type="com.prosperitasglobal.sendsolv.model.OrdemServicoTypes"/>
		<typeAlias alias="OrdemServicoStatus"              		 	 type="com.prosperitasglobal.sendsolv.model.OrdemServicoStatus"/>
		<typeAlias alias="OrdemServico"              		 		 type="com.prosperitasglobal.sendsolv.model.OrdemServico"/>
		<typeAlias alias="OrdemServicoItens"              	 		 type="com.prosperitasglobal.sendsolv.model.OrdemServicoItens"/>
		<typeAlias alias="PedidoCompras"              		 		 type="com.prosperitasglobal.sendsolv.model.PedidoCompras"/>
		<typeAlias alias="Pessoa"              		 		         type="com.prosperitasglobal.sendsolv.model.Pessoa"/>
		<typeAlias alias="Porcao"              				 		 type="com.prosperitasglobal.sendsolv.model.Porcao"/>
		<typeAlias alias="PorcaoItem"              		 		     type="com.prosperitasglobal.sendsolv.model.PorcaoItem"/>
		<typeAlias alias="TabPreco"              				 	 type="com.prosperitasglobal.sendsolv.model.TabPreco"/>
		<typeAlias alias="Plano"              		    		 	 type="com.prosperitasglobal.sendsolv.model.Plano"/>
		<typeAlias alias="Process"              				 	 type="com.prosperitasglobal.sendsolv.model.Process"/>
		<typeAlias alias="Produto"              			 		 type="com.prosperitasglobal.sendsolv.model.Produto"/>
		<typeAlias alias="ProdutoPessoa"             		 		 type="com.prosperitasglobal.sendsolv.model.ProdutoPessoa"/>
		<typeAlias alias="Profissao"              			 		 type="com.prosperitasglobal.sendsolv.model.Profissao"/>
		<typeAlias alias="Regime"              				 		 type="com.prosperitasglobal.sendsolv.model.Regime"/>
		<typeAlias alias="Rentabilidade"              		 		 type="com.prosperitasglobal.sendsolv.model.Rentabilidade"/>
		<typeAlias alias="RentabilidadeItens"              	 		 type="com.prosperitasglobal.sendsolv.model.RentabilidadeItens"/>
		<typeAlias alias="Salario"              			 		 type="com.prosperitasglobal.sendsolv.model.Salario"/>
		<typeAlias alias="Socio"              				 		 type="com.prosperitasglobal.sendsolv.model.Socio"/>
		<typeAlias alias="Status"              				 		 type="com.prosperitasglobal.sendsolv.model.Status"/>
		<typeAlias alias="SubGrupo"              			 		 type="com.prosperitasglobal.sendsolv.model.SubGrupo"/>
		<typeAlias alias="SubGrupoProd"              		 		 type="com.prosperitasglobal.sendsolv.model.SubGrupoProd"/>
		<typeAlias alias="Tabela"              				 		 type="com.prosperitasglobal.sendsolv.model.Tabela"/>
		<typeAlias alias="Tabs"              				 		 type="com.prosperitasglobal.sendsolv.model.Tabs"/>
		<typeAlias alias="Tela"              				 		 type="com.prosperitasglobal.sendsolv.model.Tela"/>
		<typeAlias alias="Telefone"              			 		 type="com.prosperitasglobal.sendsolv.model.Telefone"/>
		<typeAlias alias="Transportador"              		 		 type="com.prosperitasglobal.sendsolv.model.Transportador"/>
		<typeAlias alias="TipoPag"              		 		 	 type="com.prosperitasglobal.sendsolv.model.TipoPag"/>
		<typeAlias alias="Tributacao"              			 		 type="com.prosperitasglobal.sendsolv.model.Tributacao"/>
		<typeAlias alias="UniMed"              				 		 type="com.prosperitasglobal.sendsolv.model.UniMed"/>
		<typeAlias alias="UniMedProd"              					 type="com.prosperitasglobal.sendsolv.model.UniMedProd"/>
		<typeAlias alias="CnaeRel"              			 		 type="com.prosperitasglobal.sendsolv.model.CnaeRel"/>
		<typeAlias alias="BeneficioMesApp"              			 type="com.prosperitasglobal.sendsolv.model.BeneficioMesApp"/>
		<typeAlias alias="EmpresaInquiryRequest"           			 type="com.prosperitasglobal.sendsolv.model.request.EmpresaInquiryRequest"/>
		<typeAlias alias="CnaeInquiryRequest"            			 type="com.prosperitasglobal.sendsolv.model.request.CnaeInquiryRequest"/>
		<typeAlias alias="StatusInquiryRequest"              		 type="com.prosperitasglobal.sendsolv.model.request.StatusInquiryRequest"/>
		<typeAlias alias="FetchByIdRequest"              	         type="com.prosperitasglobal.cbof.model.request.FetchByIdRequest"/>
		<typeAlias alias="FuncionarioInquiryRequest"           		 type="com.prosperitasglobal.sendsolv.model.request.FuncionarioInquiryRequest"/>
		<typeAlias alias="ClienteInquiryRequest"            	 	 type="com.prosperitasglobal.sendsolv.model.request.ClienteInquiryRequest"/>
		<typeAlias alias="FornecedorInquiryRequest"            		 type="com.prosperitasglobal.sendsolv.model.request.FornecedorInquiryRequest"/>
		<typeAlias alias="TransportadorInquiryRequest"             	 type="com.prosperitasglobal.sendsolv.model.request.TransportadorInquiryRequest"/>
  	</typeAliases>


 	<mappers>
		<mapper resource="com/prosperitasglobal/cbof/dac/mybatis/map/cbof.xml" />
		<mapper resource="com/prosperitasglobal/sendsolv/dac/mybatis/map/agencia.xml" />
		<mapper resource="com/prosperitasglobal/sendsolv/dac/mybatis/map/arquivo.xml" />
		<mapper resource="com/prosperitasglobal/sendsolv/dac/mybatis/map/banco.xml" />
		<mapper resource="com/prosperitasglobal/sendsolv/dac/mybatis/map/beneficios.xml" />
		<mapper resource="com/prosperitasglobal/sendsolv/dac/mybatis/map/cidade.xml" />
		<mapper resource="com/prosperitasglobal/sendsolv/dac/mybatis/map/cfop.xml" />
		<mapper resource="com/prosperitasglobal/sendsolv/dac/mybatis/map/conta.xml" />
		<mapper resource="com/prosperitasglobal/sendsolv/dac/mybatis/map/caixa.xml" />
		<mapper resource="com/prosperitasglobal/sendsolv/dac/mybatis/map/classificacao.xml" />
		<mapper resource="com/prosperitasglobal/sendsolv/dac/mybatis/map/cliente.xml" />
		<mapper resource="com/prosperitasglobal/sendsolv/dac/mybatis/map/cnae.xml" />
		<mapper resource="com/prosperitasglobal/sendsolv/dac/mybatis/map/condpag.xml" />
		<mapper resource="com/prosperitasglobal/sendsolv/dac/mybatis/map/conhecimentoTransporte.xml" />
		<mapper resource="com/prosperitasglobal/sendsolv/dac/mybatis/map/contas.xml" />
		<mapper resource="com/prosperitasglobal/sendsolv/dac/mybatis/map/contato.xml" />
		<mapper resource="com/prosperitasglobal/sendsolv/dac/mybatis/map/convenio.xml" />
		<mapper resource="com/prosperitasglobal/sendsolv/dac/mybatis/map/cst.xml" />
		<mapper resource="com/prosperitasglobal/sendsolv/dac/mybatis/map/custo.xml" />
		<mapper resource="com/prosperitasglobal/sendsolv/dac/mybatis/map/custoItens.xml" />
		<mapper resource="com/prosperitasglobal/sendsolv/dac/mybatis/map/deposito.xml" />
		<mapper resource="com/prosperitasglobal/sendsolv/dac/mybatis/map/documento.xml" />
		<mapper resource="com/prosperitasglobal/sendsolv/dac/mybatis/map/email.xml" />
		<mapper resource="com/prosperitasglobal/sendsolv/dac/mybatis/map/entidade.xml" />
		<mapper resource="com/prosperitasglobal/sendsolv/dac/mybatis/map/empresa.xml" />

		<mapper resource="com/prosperitasglobal/sendsolv/dac/mybatis/map/endereco.xml" />

		<mapper resource="com/prosperitasglobal/sendsolv/dac/mybatis/map/estado.xml" />

		<mapper resource="com/prosperitasglobal/sendsolv/dac/mybatis/map/estoque.xml" />
		<mapper resource="com/prosperitasglobal/sendsolv/dac/mybatis/map/evento.xml" />
		<mapper resource="com/prosperitasglobal/sendsolv/dac/mybatis/map/filial.xml" />
		<mapper resource="com/prosperitasglobal/sendsolv/dac/mybatis/map/field.xml" />
		<mapper resource="com/prosperitasglobal/sendsolv/dac/mybatis/map/financeiro.xml" />

		<mapper resource="com/prosperitasglobal/sendsolv/dac/mybatis/map/formapg.xml" />

		<mapper resource="com/prosperitasglobal/sendsolv/dac/mybatis/map/fornecedor.xml" />
		<mapper resource="com/prosperitasglobal/sendsolv/dac/mybatis/map/funcionario.xml" />
		<mapper resource="com/prosperitasglobal/sendsolv/dac/mybatis/map/grupo.xml" />
		<mapper resource="com/prosperitasglobal/sendsolv/dac/mybatis/map/historico.xml" />
		<mapper resource="com/prosperitasglobal/sendsolv/dac/mybatis/map/historicoNF.xml" />
		<mapper resource="com/prosperitasglobal/sendsolv/dac/mybatis/map/horaFunc.xml" />
		<mapper resource="com/prosperitasglobal/sendsolv/dac/mybatis/map/incidencia.xml" />
		<mapper resource="com/prosperitasglobal/sendsolv/dac/mybatis/map/itensEspeciais.xml" />
		<mapper resource="com/prosperitasglobal/sendsolv/dac/mybatis/map/marca.xml" />
		<mapper resource="com/prosperitasglobal/sendsolv/dac/mybatis/map/nfStatus.xml" />
		<mapper resource="com/prosperitasglobal/sendsolv/dac/mybatis/map/notafiscal.xml" />
		<mapper resource="com/prosperitasglobal/sendsolv/dac/mybatis/map/nfentrada.xml" />
		<mapper resource="com/prosperitasglobal/sendsolv/dac/mybatis/map/nfsaida.xml" />
		<mapper resource="com/prosperitasglobal/cbof/dac/mybatis/map/note.xml" />
		<mapper resource="com/prosperitasglobal/sendsolv/dac/mybatis/map/notaFiscalItens.xml" />
		<mapper resource="com/prosperitasglobal/sendsolv/dac/mybatis/map/orcamento.xml" />
		<mapper resource="com/prosperitasglobal/sendsolv/dac/mybatis/map/ordemServico.xml" />
		<mapper resource="com/prosperitasglobal/sendsolv/dac/mybatis/map/ordemServicoItens.xml" />
		<mapper resource="com/prosperitasglobal/sendsolv/dac/mybatis/map/plano.xml" />
		<mapper resource="com/prosperitasglobal/sendsolv/dac/mybatis/map/pedidocompras.xml" />
		<mapper resource="com/prosperitasglobal/sendsolv/dac/mybatis/map/porcao.xml" />
		<mapper resource="com/prosperitasglobal/sendsolv/dac/mybatis/map/porcaoItens.xml" />
		<mapper resource="com/prosperitasglobal/sendsolv/dac/mybatis/map/pessoa.xml" />
		<mapper resource="com/prosperitasglobal/sendsolv/dac/mybatis/map/preco.xml" />
		<mapper resource="com/prosperitasglobal/sendsolv/dac/mybatis/map/process.xml" />
		<mapper resource="com/prosperitasglobal/sendsolv/dac/mybatis/map/produto.xml" />
		<mapper resource="com/prosperitasglobal/sendsolv/dac/mybatis/map/profissao.xml" />
		<mapper resource="com/prosperitasglobal/sendsolv/dac/mybatis/map/regime.xml" />
		<mapper resource="com/prosperitasglobal/sendsolv/dac/mybatis/map/rentabilidade.xml" />
		<mapper resource="com/prosperitasglobal/sendsolv/dac/mybatis/map/rentabilidadeItens.xml" />
		<mapper resource="com/prosperitasglobal/sendsolv/dac/mybatis/map/salarios.xml" />
		<mapper resource="com/prosperitasglobal/sendsolv/dac/mybatis/map/socios.xml" />
		<mapper resource="com/prosperitasglobal/sendsolv/dac/mybatis/map/status.xml" />
		<mapper resource="com/prosperitasglobal/sendsolv/dac/mybatis/map/subgrupo.xml" />
		<mapper resource="com/prosperitasglobal/sendsolv/dac/mybatis/map/tabela.xml" />
		<mapper resource="com/prosperitasglobal/sendsolv/dac/mybatis/map/tabs.xml" />
		<mapper resource="com/prosperitasglobal/sendsolv/dac/mybatis/map/tela.xml" />
		<mapper resource="com/prosperitasglobal/sendsolv/dac/mybatis/map/telefone.xml" />
		<mapper resource="com/prosperitasglobal/sendsolv/dac/mybatis/map/transportador.xml" />
		<mapper resource="com/prosperitasglobal/sendsolv/dac/mybatis/map/tributos.xml" />
		<mapper resource="com/prosperitasglobal/sendsolv/dac/mybatis/map/uniMed.xml" />
 	</mappers>

</configuration>
